Metadata-Version: 2.1
Name: diagram-ai-generator
Version: 1.0.6
Summary: Professional AI-powered architecture diagram generator with MCP server support
Author-email: Carlos Martínez García-Villarrubia <carlos@caricalia.com>
Maintainer-email: Carlos Martínez García-Villarrubia <carlos@caricalia.com>
Project-URL: Homepage, https://github.com/carlosmgv02/diagram-ai-generator
Project-URL: Repository, https://github.com/carlosmgv02/diagram-ai-generator
Project-URL: Documentation, https://github.com/carlosmgv02/diagram-ai-generator#readme
Project-URL: Issues, https://github.com/carlosmgv02/diagram-ai-generator/issues
Project-URL: Changelog, https://github.com/carlosmgv02/diagram-ai-generator/releases
Project-URL: Bug Reports, https://github.com/carlosmgv02/diagram-ai-generator/issues
Project-URL: Source Code, https://github.com/carlosmgv02/diagram-ai-generator
Keywords: diagrams,architecture,ai,mcp,visualization,aws,azure,gcp,kubernetes,multi-cloud,claude,infrastructure
Classifier: Development Status :: 5 - Production/Stable
Classifier: Intended Audience :: Developers
Classifier: Intended Audience :: System Administrators
Classifier: License :: OSI Approved :: MIT License
Classifier: Operating System :: OS Independent
Classifier: Programming Language :: Python :: 3
Classifier: Programming Language :: Python :: 3.10
Classifier: Programming Language :: Python :: 3.11
Classifier: Programming Language :: Python :: 3.12
Classifier: Programming Language :: Python :: 3.13
Classifier: Topic :: Software Development :: Code Generators
Classifier: Topic :: System :: Systems Administration
Classifier: Topic :: Scientific/Engineering :: Visualization
Classifier: Environment :: Console
Classifier: Natural Language :: English
Requires-Python: >=3.10
License-File: LICENSE
Requires-Dist: diagrams>=0.23.0
Requires-Dist: Pillow>=10.0.0
Requires-Dist: mcp>=0.1.0
Provides-Extra: dev
Requires-Dist: pytest>=8.0; extra == "dev"
Requires-Dist: pytest-cov>=5.0; extra == "dev"
Requires-Dist: pytest-mock>=3.12; extra == "dev"
Requires-Dist: black>=24.0; extra == "dev"
Requires-Dist: ruff>=0.3; extra == "dev"
Requires-Dist: mypy>=1.8; extra == "dev"
Requires-Dist: build>=1.0; extra == "dev"
Requires-Dist: twine>=5.0; extra == "dev"
Provides-Extra: test
Requires-Dist: pytest>=8.0; extra == "test"
Requires-Dist: pytest-cov>=5.0; extra == "test"
Requires-Dist: pytest-mock>=3.12; extra == "test"
